original_posting/__init__.py
original_posting/build.py
original_posting/builtin_names.py
original_posting/cli.py
original_posting/parsing.py
original_posting/ptag_dsl.py
original_posting/scripts/center-all.py
original_posting/scripts/code.py
original_posting/scripts/colsplit.py
original_posting/scripts/comment.py
original_posting/scripts/footnote.py
original_posting/scripts/footref.py
original_posting/scripts/img.py
original_posting/scripts/include-dir.py
original_posting/scripts/include.py
original_posting/scripts/math.py
original_posting/scripts/md.py
original_posting/scripts/plain.py
original_posting/scripts/ptag-expr.py
original_posting/scripts/ptag-filter-index.py
original_posting/scripts/ptag-pat.py
original_posting/scripts/ptag-set.py
original_posting/scripts/py.py
original_posting/scripts/pygments_styles/base16_applepips_light.py
original_posting/scripts/pygments_styles/quiet_light.py
original_posting/scripts/raw-include.py
original_posting/scripts/raw-link.py
original_posting/scripts/ref.py
original_posting/scripts/set-index-format.py
original_posting/scripts/toc.py
original_posting/types.py
original_posting/utils.py
original_posting-0.4.0.dist-info/entry_points.txt
original_posting-0.4.0.dist-info/METADATA
original_posting-0.4.0.dist-info/WHEEL
original_posting-0.4.0.dist-info/RECORD
