Metadata-Version: 2.1
Name: original-posting
Version: 0.4.0
Summary: 
Author: thautwarm
Author-email: twshere@outlook.com
Requires-Python: >=3.9,<4.0
Classifier: Programming Language :: Python :: 3
Classifier: Programming Language :: Python :: 3.9
Classifier: Programming Language :: Python :: 3.10
Classifier: Programming Language :: Python :: 3.11
Requires-Dist: beautifulsoup4 (>=4.11.1,<5.0.0)
Requires-Dist: diskcache (>=5.4.0,<6.0.0)
Requires-Dist: wisepy2 (>=1.3,<2.0)
